scrape2md/__init__.py
scrape2md/cli.py
scrape2md/py.typed
scrape2md/scraper.py
scrape2md-0.1.0.dist-info/licenses/LICENSE
scrape2md-0.1.0.dist-info/METADATA
scrape2md-0.1.0.dist-info/WHEEL
scrape2md-0.1.0.dist-info/entry_points.txt
scrape2md-0.1.0.dist-info/top_level.txt
scrape2md-0.1.0.dist-info/RECORD
