Metadata-Version: 2.4
Name: scrape2md
Version: 0.1.0
Summary: Scrape websites and convert them to clean markdown format
Author-email: Anand Taralika <hello@anand.id>
License-Expression: MIT
Project-URL: Homepage, https://github.com/taralika/scrape2md
Project-URL: Repository, https://github.com/taralika/scrape2md
Project-URL: Issues, https://github.com/taralika/scrape2md/issues
Keywords: scraper,markdown,web-scraping,html-to-markdown,crawler
Classifier: Development Status :: 4 - Beta
Classifier: Intended Audience :: Developers
Classifier: Programming Language :: Python :: 3
Classifier: Programming Language :: Python :: 3.8
Classifier: Programming Language :: Python :: 3.9
Classifier: Programming Language :: Python :: 3.10
Classifier: Programming Language :: Python :: 3.11
Classifier: Programming Language :: Python :: 3.12
Classifier: Topic :: Internet :: WWW/HTTP
Classifier: Topic :: Software Development :: Libraries :: Python Modules
Classifier: Topic :: Text Processing :: Markup :: Markdown
Requires-Python: >=3.8
License-File: LICENSE
Requires-Dist: playwright>=1.48.0
Requires-Dist: beautifulsoup4>=4.12.3
Requires-Dist: html2text>=2020.1.16
Requires-Dist: requests>=2.31.0
Provides-Extra: dev
Requires-Dist: pytest>=7.0; extra == "dev"
Requires-Dist: pytest-cov>=4.0; extra == "dev"
Requires-Dist: black>=23.0; extra == "dev"
Requires-Dist: ruff>=0.1.0; extra == "dev"
Requires-Dist: mypy>=1.0; extra == "dev"
Dynamic: license-file
